exchange_calendars/__init__.py
exchange_calendars/_version.py
exchange_calendars/always_open.py
exchange_calendars/calendar_helpers.py
exchange_calendars/calendar_utils.py
exchange_calendars/common_holidays.py
exchange_calendars/ecal.py
exchange_calendars/errors.py
exchange_calendars/exchange_calendar.py
exchange_calendars/exchange_calendar_aixk.py
exchange_calendars/exchange_calendar_asex.py
exchange_calendars/exchange_calendar_bvmf.py
exchange_calendars/exchange_calendar_cmes.py
exchange_calendars/exchange_calendar_iepa.py
exchange_calendars/exchange_calendar_tejxtai.py
exchange_calendars/exchange_calendar_tejxtai_morning_future.py
exchange_calendars/exchange_calendar_xams.py
exchange_calendars/exchange_calendar_xasx.py
exchange_calendars/exchange_calendar_xbkk.py
exchange_calendars/exchange_calendar_xbog.py
exchange_calendars/exchange_calendar_xbom.py
exchange_calendars/exchange_calendar_xbru.py
exchange_calendars/exchange_calendar_xbse.py
exchange_calendars/exchange_calendar_xbud.py
exchange_calendars/exchange_calendar_xbue.py
exchange_calendars/exchange_calendar_xcbf.py
exchange_calendars/exchange_calendar_xcse.py
exchange_calendars/exchange_calendar_xdub.py
exchange_calendars/exchange_calendar_xetr.py
exchange_calendars/exchange_calendar_xfra.py
exchange_calendars/exchange_calendar_xhel.py
exchange_calendars/exchange_calendar_xhkg.py
exchange_calendars/exchange_calendar_xice.py
exchange_calendars/exchange_calendar_xidx.py
exchange_calendars/exchange_calendar_xist.py
exchange_calendars/exchange_calendar_xjse.py
exchange_calendars/exchange_calendar_xkar.py
exchange_calendars/exchange_calendar_xkls.py
exchange_calendars/exchange_calendar_xkrx.py
exchange_calendars/exchange_calendar_xlim.py
exchange_calendars/exchange_calendar_xlis.py
exchange_calendars/exchange_calendar_xlon.py
exchange_calendars/exchange_calendar_xmad.py
exchange_calendars/exchange_calendar_xmex.py
exchange_calendars/exchange_calendar_xmil.py
exchange_calendars/exchange_calendar_xmos.py
tej_exchange_calendars-1.0.1.dist-info/licenses/LICENSE
tej_exchange_calendars-1.0.1.dist-info/METADATA
tej_exchange_calendars-1.0.1.dist-info/WHEEL
tej_exchange_calendars-1.0.1.dist-info/entry_points.txt
tej_exchange_calendars-1.0.1.dist-info/top_level.txt
tej_exchange_calendars-1.0.1.dist-info/RECORD
