Metadata-Version: 2.4
Name: tej-exchange-calendars
Version: 1.0.1
Summary: Calendars for securities exchanges
Author: tej
Author-email: tej@tej.com.tw
Maintainer: tej api Development Team
Maintainer-email: tej@tej.com.tw
License: Apache-2.0
Project-URL: homepage, https://tquant.tejwin.com/
Project-URL: repository, https://github.com/tejtw/exchange_calendars
Keywords: finance,security,calendar,exchange
Classifier: Development Status :: 4 - Beta
Classifier: Programming Language :: Python
Classifier: Programming Language :: Python :: 3
Classifier: Programming Language :: Python :: 3.9
Classifier: Programming Language :: Python :: 3.10
Classifier: Programming Language :: Python :: 3.11
Classifier: Programming Language :: Python :: 3.12
Classifier: License :: OSI Approved :: Apache Software License
Classifier: Intended Audience :: Science/Research
Classifier: Topic :: Scientific/Engineering
Classifier: Topic :: Scientific/Engineering :: Mathematics
Classifier: Operating System :: OS Independent
Requires-Python: ~=3.8
License-File: LICENSE
Requires-Dist: numpy>=2
Requires-Dist: pandas>=2.0.0
Requires-Dist: pyluach
Requires-Dist: toolz
Requires-Dist: tzdata
Requires-Dist: korean_lunar_calendar
Provides-Extra: dev
Requires-Dist: flake8; extra == "dev"
Requires-Dist: hypothesis; extra == "dev"
Requires-Dist: pytest; extra == "dev"
Requires-Dist: pytest-benchmark; extra == "dev"
Requires-Dist: pytest-xdist; extra == "dev"
Requires-Dist: pip-tools; extra == "dev"
Dynamic: license-file
